source_polygon_stock_api/__init__.py
source_polygon_stock_api/manifest.yaml
source_polygon_stock_api/run.py
source_polygon_stock_api/source.py
airbyte_source_polygon_stock_api-0.1.17.dist-info/METADATA
airbyte_source_polygon_stock_api-0.1.17.dist-info/WHEEL
airbyte_source_polygon_stock_api-0.1.17.dist-info/entry_points.txt
airbyte_source_polygon_stock_api-0.1.17.dist-info/RECORD
