Metadata-Version: 2.1
Name: airbyte-source-polygon-stock-api
Version: 0.1.17
Summary: Source implementation for Polygon Stock Api.
Home-page: https://airbyte.com
License: MIT
Author: Airbyte
Author-email: contact@airbyte.io
Requires-Python: >=3.9,<3.12
Classifier: License :: OSI Approved :: MIT License
Classifier: Programming Language :: Python :: 3
Classifier: Programming Language :: Python :: 3.9
Classifier: Programming Language :: Python :: 3.10
Classifier: Programming Language :: Python :: 3.11
Requires-Dist: airbyte-cdk (==0.80.0)
Project-URL: Documentation, https://docs.airbyte.com/integrations/sources/polygon-stock-api
Project-URL: Repository, https://github.com/airbytehq/airbyte
